MANIFEST.in
README.md
setup.py
tormetron/__init__.py
tormetron/__main__.py
tormetron/config.cfg
tormetron/constants.py
tormetron/radares.py
tormetron.egg-info/PKG-INFO
tormetron/radardata/cod_ccaa.csv
tormetron/radardata/cod_ccaa.json
tormetron/radardata/cod_radar_regional.csv
tormetron/radardata/cod_radar_regional.json
tormetron/radardata/cod_radar_regional_algunos.json
tormetron/radardata/cod_radar_regional_completo.json
tormetron/radardata/municipios.csv
tormetron/radardata/municipios.json